fastapi_xroad_soap/__init__.py
fastapi_xroad_soap/elements.py
fastapi_xroad_soap/faults.py
fastapi_xroad_soap/internal/__init__.py
fastapi_xroad_soap/internal/base/__init__.py
fastapi_xroad_soap/internal/base/base_element_spec.py
fastapi_xroad_soap/internal/base/composite_meta.py
fastapi_xroad_soap/internal/base/dynamic_spec.py
fastapi_xroad_soap/internal/base/message_body.py
fastapi_xroad_soap/internal/base/validators.py
fastapi_xroad_soap/internal/constants.py
fastapi_xroad_soap/internal/elements/__init__.py
fastapi_xroad_soap/internal/elements/models/__init__.py
fastapi_xroad_soap/internal/elements/models/boolean.py
fastapi_xroad_soap/internal/elements/models/date.py
fastapi_xroad_soap/internal/elements/models/datetime.py
fastapi_xroad_soap/internal/elements/models/float.py
fastapi_xroad_soap/internal/elements/models/integer.py
fastapi_xroad_soap/internal/elements/models/netres.py
fastapi_xroad_soap/internal/elements/models/string.py
fastapi_xroad_soap/internal/elements/models/swaref.py
fastapi_xroad_soap/internal/elements/models/time.py
fastapi_xroad_soap/internal/elements/numeric_type_spec.py
fastapi_xroad_soap/internal/elements/string_type_spec.py
fastapi_xroad_soap/internal/elements/validators.py
fastapi_xroad_soap/internal/envelope/__init__.py
fastapi_xroad_soap/internal/envelope/factory.py
fastapi_xroad_soap/internal/envelope/generics.py
fastapi_xroad_soap/internal/envelope/header.py
fastapi_xroad_soap/internal/file_size.py
fastapi_xroad_soap/internal/multipart/__init__.py
fastapi_xroad_soap/internal/multipart/bodypart.py
fastapi_xroad_soap/internal/multipart/decoder.py
fastapi_xroad_soap/internal/multipart/encoder.py
fastapi_xroad_soap/internal/multipart/errors.py
fastapi_xroad_soap/internal/soap/__init__.py
fastapi_xroad_soap/internal/soap/action.py
fastapi_xroad_soap/internal/soap/faults.py
fastapi_xroad_soap/internal/soap/response.py
fastapi_xroad_soap/internal/soap/service.py
fastapi_xroad_soap/internal/soap/service.pyi
fastapi_xroad_soap-0.4.7.dist-info/LICENSE
fastapi_xroad_soap-0.4.7.dist-info/METADATA
fastapi_xroad_soap-0.4.7.dist-info/WHEEL
fastapi_xroad_soap-0.4.7.dist-info/RECORD
